praiso/__init__.py
praiso-0.0.1.dist-info/METADATA
praiso-0.0.1.dist-info/WHEEL
praiso-0.0.1.dist-info/licenses/LICENSE
praiso-0.0.1.dist-info/RECORD
