Metadata-Version: 2.4
Name: praiso
Version: 0.0.1
Summary: A Python package
Project-URL: Homepage, https://github.com/praison/praiso
Author: MervinPraison
License: MIT License
License-File: LICENSE
Classifier: License :: OSI Approved :: MIT License
Classifier: Operating System :: OS Independent
Classifier: Programming Language :: Python :: 3
Requires-Python: >=3.6
